{
  "canvas": {
    "version": "2.2.13",
    "width": 2000,
    "height": 2000,
    "scrollTop": -131.70810000000006,
    "scrollLeft": -468.322,
    "zoomLevel": 0.8,
    "show": {
      "tableComment": true,
      "columnComment": true,
      "columnDataType": true,
      "columnDefault": true,
      "columnAutoIncrement": false,
      "columnPrimaryKey": true,
      "columnUnique": false,
      "columnNotNull": true,
      "relationship": true
    },
    "database": "MySQL",
    "databaseName": "",
    "canvasType": "@vuerd/builtin-sql-ddl",
    "language": "GraphQL",
    "tableCase": "pascalCase",
    "columnCase": "camelCase",
    "highlightTheme": "VS2015",
    "bracketType": "none",
    "setting": {
      "relationshipDataTypeSync": true,
      "relationshipOptimization": false,
      "columnOrder": [
        "columnName",
        "columnDataType",
        "columnNotNull",
        "columnUnique",
        "columnAutoIncrement",
        "columnDefault",
        "columnComment"
      ]
    },
    "pluginSerializationMap": {}
  },
  "table": {
    "tables": [
      {
        "id": "5a64e898-5e75-45f5-b269-84ad8e0f571a",
        "name": "user",
        "comment": "사용자 테이블",
        "columns": [
          {
            "id": "ef92b31d-e57d-4e22-9759-b3b31a75c982",
            "name": "email",
            "comment": "사용자 이메일",
            "dataType": "VARCHAR(50)",
            "default": "",
            "option": {
              "autoIncrement": false,
              "primaryKey": true,
              "unique": false,
              "notNull": true
            },
            "ui": {
              "active": false,
              "pk": true,
              "fk": false,
              "pfk": false,
              "widthName": 60,
              "widthComment": 84.5703125,
              "widthDataType": 82.1328125,
              "widthDefault": 60
            }
          },
          {
            "id": "5f5036a7-4ba7-47c0-8f47-c5f5e1d5d8b0",
            "name": "password",
            "comment": "사용자 비밀번호",
            "dataType": "VARCHAR(50)",
            "default": "",
            "option": {
              "autoIncrement": false,
              "primaryKey": false,
              "unique": false,
              "notNull": true
            },
            "ui": {
              "active": false,
              "pk": false,
              "fk": false,
              "pfk": false,
              "widthName": 60,
              "widthComment": 97.5703125,
              "widthDataType": 82.1328125,
              "widthDefault": 60
            }
          },
          {
            "id": "94f2f557-33e3-423b-aaf1-585b1afc499c",
            "name": "nickname",
            "comment": "사용자 닉네임",
            "dataType": "VARCHAR(20)",
            "default": "",
            "option": {
              "autoIncrement": false,
              "primaryKey": false,
              "unique": false,
              "notNull": true
            },
            "ui": {
              "active": false,
              "pk": false,
              "fk": false,
              "pfk": false,
              "widthName": 60,
              "widthComment": 84.5703125,
              "widthDataType": 82.1328125,
              "widthDefault": 60
            }
          },
          {
            "id": "68a83a3e-6fd5-48d2-bbe8-73674cc50f72",
            "name": "tel_number",
            "comment": "사용자 휴대전화번호",
            "dataType": "VARCHAR(15)",
            "default": "",
            "option": {
              "autoIncrement": false,
              "primaryKey": false,
              "unique": false,
              "notNull": true
            },
            "ui": {
              "active": false,
              "pk": false,
              "fk": false,
              "pfk": false,
              "widthName": 67.89501953125,
              "widthComment": 120,
              "widthDataType": 82.1328125,
              "widthDefault": 60
            }
          },
          {
            "id": "ad26332e-8911-49c9-9db2-8c4c6bbf469b",
            "name": "address",
            "comment": "사용자 주소",
            "dataType": "TEXT",
            "default": "",
            "option": {
              "autoIncrement": false,
              "primaryKey": false,
              "unique": false,
              "notNull": true
            },
            "ui": {
              "active": false,
              "pk": false,
              "fk": false,
              "pfk": false,
              "widthName": 60,
              "widthComment": 71.5703125,
              "widthDataType": 60,
              "widthDefault": 60
            }
          },
          {
            "id": "5425818f-a7ef-4146-b8da-3a1c4f686afe",
            "name": "address_detail",
            "comment": "사용자 상세 주소",
            "dataType": "TEXT",
            "default": "",
            "option": {
              "autoIncrement": false,
              "primaryKey": false,
              "unique": false,
              "notNull": false
            },
            "ui": {
              "active": false,
              "pk": false,
              "fk": false,
              "pfk": false,
              "widthName": 85.001953125,
              "widthComment": 102.140625,
              "widthDataType": 60,
              "widthDefault": 60
            }
          },
          {
            "id": "ff9572bb-6cf5-47c4-80fb-24b9ce2ebd48",
            "name": "profile_image",
            "comment": "사용자 프로필 사진",
            "dataType": "TEXT",
            "default": "",
            "option": {
              "autoIncrement": false,
              "primaryKey": false,
              "unique": false,
              "notNull": false
            },
            "ui": {
              "active": false,
              "pk": false,
              "fk": false,
              "pfk": false,
              "widthName": 80.939453125,
              "widthComment": 115.140625,
              "widthDataType": 60,
              "widthDefault": 60
            }
          }
        ],
        "ui": {
          "active": false,
          "left": 60.7226,
          "top": 372.2225,
          "zIndex": 413,
          "widthName": 60,
          "widthComment": 84.5703125,
          "color": "#FFC107"
        },
        "visible": true
      },
      {
        "id": "8f6718eb-5136-45ba-a3a8-8f312ca06a84",
        "name": "board",
        "comment": "게시물 테이블",
        "columns": [
          {
            "id": "77ecaec8-e3db-4c38-a3a0-52ba822edbfb",
            "name": "board_number",
            "comment": "게시물 번호",
            "dataType": "INT",
            "default": "AUTO_INCREMENT",
            "option": {
              "autoIncrement": false,
              "primaryKey": true,
              "unique": false,
              "notNull": true
            },
            "ui": {
              "active": false,
              "pk": true,
              "fk": false,
              "pfk": false,
              "widthName": 87.77587890625,
              "widthComment": 71.5703125,
              "widthDataType": 60,
              "widthDefault": 113.29345703125
            }
          },
          {
            "id": "f0f74314-8abf-4d90-88c7-4f3265c49377",
            "name": "title",
            "comment": "게시물 제목",
            "dataType": "TEXT",
            "default": "",
            "option": {
              "autoIncrement": false,
              "primaryKey": false,
              "unique": false,
              "notNull": true
            },
            "ui": {
              "active": false,
              "pk": false,
              "fk": false,
              "pfk": false,
              "widthName": 60,
              "widthComment": 71.5703125,
              "widthDataType": 60,
              "widthDefault": 60
            }
          },
          {
            "id": "25a7ef6c-6c81-44aa-8451-e9e9d7aa52cf",
            "name": "content",
            "comment": "게시물 내용",
            "dataType": "TEXT",
            "default": "",
            "option": {
              "autoIncrement": false,
              "primaryKey": false,
              "unique": false,
              "notNull": true
            },
            "ui": {
              "active": false,
              "pk": false,
              "fk": false,
              "pfk": false,
              "widthName": 60,
              "widthComment": 71.5703125,
              "widthDataType": 60,
              "widthDefault": 60
            }
          },
          {
            "id": "254e6e45-0d04-4cc5-af2d-8cc9bcf9f2e6",
            "name": "write_datetime",
            "comment": "게시물 작성 날짜 및 시간",
            "dataType": "DATETIME",
            "default": "",
            "option": {
              "autoIncrement": false,
              "primaryKey": false,
              "unique": false,
              "notNull": true
            },
            "ui": {
              "active": false,
              "pk": false,
              "fk": false,
              "pfk": false,
              "widthName": 88.2265625,
              "widthComment": 120,
              "widthDataType": 61.42041015625,
              "widthDefault": 60
            }
          },
          {
            "id": "90c637a9-1df8-4c99-b6b8-11320989d665",
            "name": "favorite_count",
            "comment": "게시물 좋아요 수",
            "dataType": "INT",
            "default": "0",
            "option": {
              "autoIncrement": false,
              "primaryKey": false,
              "unique": false,
              "notNull": true
            },
            "ui": {
              "active": false,
              "pk": false,
              "fk": false,
              "pfk": false,
              "widthName": 85.02099609375,
              "widthComment": 102.140625,
              "widthDataType": 60,
              "widthDefault": 60
            }
          },
          {
            "id": "eb8ddeff-d0df-492e-9f37-72b676159c89",
            "name": "comment_count",
            "comment": "게시물 댓글 수",
            "dataType": "INT",
            "default": "0",
            "option": {
              "autoIncrement": false,
              "primaryKey": false,
              "unique": false,
              "notNull": true
            },
            "ui": {
              "active": false,
              "pk": false,
              "fk": false,
              "pfk": false,
              "widthName": 96.7451171875,
              "widthComment": 89.140625,
              "widthDataType": 60,
              "widthDefault": 60
            }
          },
          {
            "id": "21162156-5f7e-40c6-adb6-970d7f616c49",
            "name": "view_count",
            "comment": "게시물 조회 수",
            "dataType": "INT",
            "default": "0",
            "option": {
              "autoIncrement": false,
              "primaryKey": false,
              "unique": false,
              "notNull": true
            },
            "ui": {
              "active": false,
              "pk": false,
              "fk": false,
              "pfk": false,
              "widthName": 67.04443359375,
              "widthComment": 89.140625,
              "widthDataType": 60,
              "widthDefault": 60
            }
          },
          {
            "id": "73ce8c33-b65a-4fdb-b694-68541eba5fef",
            "name": "write_email",
            "comment": "게시물 작성자 이메일",
            "dataType": "VARCHAR(50)",
            "default": "",
            "option": {
              "autoIncrement": false,
              "primaryKey": false,
              "unique": false,
              "notNull": true
            },
            "ui": {
              "active": false,
              "pk": false,
              "fk": true,
              "pfk": false,
              "widthName": 67.787109375,
              "widthComment": 120,
              "widthDataType": 82.1328125,
              "widthDefault": 60
            }
          }
        ],
        "ui": {
          "active": false,
          "left": 648.9869,
          "top": 376.4197,
          "zIndex": 421,
          "widthName": 60,
          "widthComment": 84.5703125,
          "color": "#3F51B5"
        },
        "visible": true
      },
      {
        "id": "fa7a5a35-a41f-40b9-a5d7-53bb65e543c6",
        "name": "image",
        "comment": "게시물 이미지 테이블",
        "columns": [
          {
            "id": "32d3f4d2-a110-45ee-b56a-b7476c92e95f",
            "name": "board_number",
            "comment": "게시물 번호",
            "dataType": "INT",
            "default": "AUTO_INCREMENT",
            "option": {
              "autoIncrement": false,
              "primaryKey": false,
              "unique": false,
              "notNull": true
            },
            "ui": {
              "active": false,
              "pk": false,
              "fk": true,
              "pfk": false,
              "widthName": 87.77587890625,
              "widthComment": 71.5703125,
              "widthDataType": 60,
              "widthDefault": 113.29345703125
            }
          },
          {
            "id": "34ecb3ab-9142-4f6c-a0e6-1fd49fd9a116",
            "name": "image",
            "comment": "게시물 이미지 URL",
            "dataType": "TEXT",
            "default": "",
            "option": {
              "autoIncrement": false,
              "primaryKey": false,
              "unique": false,
              "notNull": false
            },
            "ui": {
              "active": false,
              "pk": false,
              "fk": false,
              "pfk": false,
              "widthName": 60,
              "widthComment": 112.44287109375,
              "widthDataType": 60,
              "widthDefault": 60
            }
          }
        ],
        "ui": {
          "active": false,
          "left": 1272.2092,
          "top": 110.4472,
          "zIndex": 425,
          "widthName": 60,
          "widthComment": 120,
          "color": "#E91E63"
        },
        "visible": true
      },
      {
        "id": "f6563b05-713d-4f09-b16a-a761fbaa2fa6",
        "name": "favorite",
        "comment": "좋아요 테이블",
        "columns": [
          {
            "id": "34d6113f-e285-491e-b322-ee191195e5a2",
            "name": "user_email",
            "comment": "사용자 이메일",
            "dataType": "VARCHAR(50)",
            "default": "",
            "option": {
              "autoIncrement": false,
              "primaryKey": true,
              "unique": false,
              "notNull": true
            },
            "ui": {
              "active": false,
              "pk": false,
              "fk": false,
              "pfk": true,
              "widthName": 63.7880859375,
              "widthComment": 84.5703125,
              "widthDataType": 82.1328125,
              "widthDefault": 60
            }
          },
          {
            "id": "d5a65855-27be-43cf-a0fd-3b88be1015a6",
            "name": "board_number",
            "comment": "게시물 번호",
            "dataType": "INT",
            "default": "AUTO_INCREMENT",
            "option": {
              "autoIncrement": false,
              "primaryKey": true,
              "unique": false,
              "notNull": true
            },
            "ui": {
              "active": false,
              "pk": false,
              "fk": false,
              "pfk": true,
              "widthName": 87.77587890625,
              "widthComment": 71.5703125,
              "widthDataType": 60,
              "widthDefault": 113.29345703125
            }
          }
        ],
        "ui": {
          "active": false,
          "left": 428.5,
          "top": 123.5213,
          "zIndex": 423,
          "widthName": 60,
          "widthComment": 84.5703125
        },
        "visible": true
      },
      {
        "id": "a5a9f514-eceb-45c9-a6d3-3796c377c0b8",
        "name": "comment",
        "comment": "댓글 테이블",
        "columns": [
          {
            "id": "f5338cc4-8314-45cd-8dc5-d0a381299d56",
            "name": "comment_number",
            "comment": "댓글 번호",
            "dataType": "INT",
            "default": "",
            "option": {
              "autoIncrement": false,
              "primaryKey": true,
              "unique": false,
              "notNull": true
            },
            "ui": {
              "active": false,
              "pk": true,
              "fk": false,
              "pfk": false,
              "widthName": 109.12939453125,
              "widthComment": 60,
              "widthDataType": 60,
              "widthDefault": 60
            }
          },
          {
            "id": "dff148ef-8286-4bc5-8948-61e375556918",
            "name": "content",
            "comment": "댓글 내용",
            "dataType": "TEXT",
            "default": "",
            "option": {
              "autoIncrement": false,
              "primaryKey": false,
              "unique": false,
              "notNull": true
            },
            "ui": {
              "active": false,
              "pk": false,
              "fk": false,
              "pfk": false,
              "widthName": 60,
              "widthComment": 60,
              "widthDataType": 60,
              "widthDefault": 60
            }
          },
          {
            "id": "97239be3-898c-4ff9-9600-900987283bfc",
            "name": "write_datetime",
            "comment": "작성 날짜 및 시간",
            "dataType": "DATETIME",
            "default": "",
            "option": {
              "autoIncrement": false,
              "primaryKey": false,
              "unique": false,
              "notNull": true
            },
            "ui": {
              "active": false,
              "pk": false,
              "fk": false,
              "pfk": false,
              "widthName": 88.2265625,
              "widthComment": 106.7109375,
              "widthDataType": 61.42041015625,
              "widthDefault": 60
            }
          },
          {
            "id": "20a8cef4-4d18-420a-957c-94556e54a177",
            "name": "user_email",
            "comment": "사용자 이메일",
            "dataType": "VARCHAR(50)",
            "default": "",
            "option": {
              "autoIncrement": false,
              "primaryKey": false,
              "unique": false,
              "notNull": true
            },
            "ui": {
              "active": false,
              "pk": false,
              "fk": true,
              "pfk": false,
              "widthName": 63.7880859375,
              "widthComment": 84.5703125,
              "widthDataType": 82.1328125,
              "widthDefault": 60
            }
          },
          {
            "id": "fdd61774-a6b2-4fde-a58a-bf5e10e17af9",
            "name": "board_number",
            "comment": "게시물 번호",
            "dataType": "INT",
            "default": "AUTO_INCREMENT",
            "option": {
              "autoIncrement": false,
              "primaryKey": false,
              "unique": false,
              "notNull": true
            },
            "ui": {
              "active": false,
              "pk": false,
              "fk": true,
              "pfk": false,
              "widthName": 87.77587890625,
              "widthComment": 71.5703125,
              "widthDataType": 60,
              "widthDefault": 113.29345703125
            }
          }
        ],
        "ui": {
          "active": false,
          "left": 357,
          "top": 706.0213,
          "zIndex": 410,
          "widthName": 60,
          "widthComment": 71.5703125,
          "color": "#8BC34A"
        },
        "visible": true
      },
      {
        "id": "eb74f571-7d84-4ccf-bf6d-37f26c9349e7",
        "name": "search_log",
        "comment": "검색 기록 테이블",
        "columns": [
          {
            "id": "e42b7380-36c9-433c-9d6e-1982cc900108",
            "name": "sequence",
            "comment": "시퀀스",
            "dataType": "INT",
            "default": "",
            "option": {
              "autoIncrement": false,
              "primaryKey": true,
              "unique": false,
              "notNull": true
            },
            "ui": {
              "active": false,
              "pk": true,
              "fk": false,
              "pfk": false,
              "widthName": 60,
              "widthComment": 60,
              "widthDataType": 60,
              "widthDefault": 60
            }
          },
          {
            "id": "7b676fa8-3852-483d-82a3-eac1d8e2cb2c",
            "name": "search_word",
            "comment": "검색어",
            "dataType": "TEXT",
            "default": "",
            "option": {
              "autoIncrement": false,
              "primaryKey": false,
              "unique": false,
              "notNull": true
            },
            "ui": {
              "active": false,
              "pk": false,
              "fk": false,
              "pfk": false,
              "widthName": 74.52197265625,
              "widthComment": 60,
              "widthDataType": 60,
              "widthDefault": 60
            }
          },
          {
            "id": "e775ae94-d880-4798-8299-9952fcfef183",
            "name": "relation_word",
            "comment": "관련 검색어",
            "dataType": "TEXT",
            "default": "",
            "option": {
              "autoIncrement": false,
              "primaryKey": false,
              "unique": false,
              "notNull": false
            },
            "ui": {
              "active": false,
              "pk": false,
              "fk": false,
              "pfk": false,
              "widthName": 81.4091796875,
              "widthComment": 71.5703125,
              "widthDataType": 60,
              "widthDefault": 60
            }
          },
          {
            "id": "bf94b5ac-f848-4332-8fca-043d16db61d5",
            "name": "relation",
            "comment": "관련 검색어 여부",
            "dataType": "BOOLEAN",
            "default": "",
            "option": {
              "autoIncrement": false,
              "primaryKey": false,
              "unique": false,
              "notNull": true
            },
            "ui": {
              "active": false,
              "pk": false,
              "fk": false,
              "pfk": false,
              "widthName": 60,
              "widthComment": 102.140625,
              "widthDataType": 61.22998046875,
              "widthDefault": 60
            }
          }
        ],
        "ui": {
          "active": false,
          "left": 1021.5,
          "top": 687,
          "zIndex": 399,
          "widthName": 63.775390625,
          "widthComment": 102.140625,
          "color": "#009688"
        },
        "visible": true
      }
    ],
    "indexes": []
  },
  "memo": {
    "memos": []
  },
  "relationship": {
    "relationships": [
      {
        "id": "0f27ceca-a6ca-40b9-9b09-bb291a1958c7",
        "identification": false,
        "relationshipType": "ZeroN",
        "startRelationshipType": "Dash",
        "start": {
          "tableId": "8f6718eb-5136-45ba-a3a8-8f312ca06a84",
          "columnIds": [
            "77ecaec8-e3db-4c38-a3a0-52ba822edbfb"
          ],
          "x": 1168.1582867187499,
          "y": 492.9197,
          "direction": "right"
        },
        "end": {
          "tableId": "fa7a5a35-a41f-40b9-a5d7-53bb65e543c6",
          "columnIds": [
            "32d3f4d2-a110-45ee-b56a-b7476c92e95f"
          ],
          "x": 1272.2092,
          "y": 165.4472,
          "direction": "left"
        },
        "constraintName": "fk_board_to_image",
        "visible": true
      },
      {
        "id": "380a0725-a5b1-46a9-8d86-9eab300bd1f0",
        "identification": false,
        "relationshipType": "ZeroN",
        "startRelationshipType": "Dash",
        "start": {
          "tableId": "5a64e898-5e75-45f5-b269-84ad8e0f571a",
          "columnIds": [
            "ef92b31d-e57d-4e22-9759-b3b31a75c982"
          ],
          "x": 514.857365625,
          "y": 478.4725,
          "direction": "right"
        },
        "end": {
          "tableId": "8f6718eb-5136-45ba-a3a8-8f312ca06a84",
          "columnIds": [
            "73ce8c33-b65a-4fdb-b694-68541eba5fef"
          ],
          "x": 648.9869,
          "y": 492.9197,
          "direction": "left"
        },
        "constraintName": "fk_user_to_board",
        "visible": true
      },
      {
        "id": "d934ceaf-abe0-4c3a-b860-17ddd7dc46ce",
        "identification": true,
        "relationshipType": "ZeroN",
        "startRelationshipType": "Dash",
        "start": {
          "tableId": "5a64e898-5e75-45f5-b269-84ad8e0f571a",
          "columnIds": [
            "ef92b31d-e57d-4e22-9759-b3b31a75c982"
          ],
          "x": 287.7899828125,
          "y": 372.2225,
          "direction": "top"
        },
        "end": {
          "tableId": "f6563b05-713d-4f09-b16a-a761fbaa2fa6",
          "columnIds": [
            "34d6113f-e285-491e-b322-ee191195e5a2"
          ],
          "x": 428.5,
          "y": 178.5213,
          "direction": "left"
        },
        "constraintName": "fk_user_to_favorite",
        "visible": true
      },
      {
        "id": "ff14a2e2-8ee2-45bb-a251-74bf6151c9d4",
        "identification": true,
        "relationshipType": "ZeroN",
        "startRelationshipType": "Dash",
        "start": {
          "tableId": "8f6718eb-5136-45ba-a3a8-8f312ca06a84",
          "columnIds": [
            "77ecaec8-e3db-4c38-a3a0-52ba822edbfb"
          ],
          "x": 908.572593359375,
          "y": 376.4197,
          "direction": "top"
        },
        "end": {
          "tableId": "f6563b05-713d-4f09-b16a-a761fbaa2fa6",
          "columnIds": [
            "d5a65855-27be-43cf-a0fd-3b88be1015a6"
          ],
          "x": 903.2724609375,
          "y": 178.5213,
          "direction": "right"
        },
        "constraintName": "fk_board_to_favorite",
        "visible": true
      },
      {
        "id": "c85cbc83-6ad8-4800-a6cc-c53fb3470ca0",
        "identification": false,
        "relationshipType": "ZeroN",
        "startRelationshipType": "Dash",
        "start": {
          "tableId": "5a64e898-5e75-45f5-b269-84ad8e0f571a",
          "columnIds": [
            "ef92b31d-e57d-4e22-9759-b3b31a75c982"
          ],
          "x": 287.7899828125,
          "y": 584.7225000000001,
          "direction": "bottom"
        },
        "end": {
          "tableId": "a5a9f514-eceb-45c9-a6d3-3796c377c0b8",
          "columnIds": [
            "20a8cef4-4d18-420a-957c-94556e54a177"
          ],
          "x": 357,
          "y": 791.7713,
          "direction": "left"
        },
        "constraintName": "fk_user_to_comment",
        "visible": true
      },
      {
        "id": "1ea65af4-7890-40bb-b4b0-4b7beeec8f99",
        "identification": false,
        "relationshipType": "ZeroN",
        "startRelationshipType": "Dash",
        "start": {
          "tableId": "8f6718eb-5136-45ba-a3a8-8f312ca06a84",
          "columnIds": [
            "77ecaec8-e3db-4c38-a3a0-52ba822edbfb"
          ],
          "x": 908.572593359375,
          "y": 609.4196999999999,
          "direction": "bottom"
        },
        "end": {
          "tableId": "a5a9f514-eceb-45c9-a6d3-3796c377c0b8",
          "columnIds": [
            "fdd61774-a6b2-4fde-a58a-bf5e10e17af9"
          ],
          "x": 875.2666015625,
          "y": 791.7713,
          "direction": "right"
        },
        "constraintName": "fk_board_to_comment",
        "visible": true
      }
    ]
  }
}